pylint_single_element_destructuring/__init__.py
pylint_single_element_destructuring/checker.py
pylint_single_element_destructuring-0.1.1.dist-info/WHEEL
pylint_single_element_destructuring-0.1.1.dist-info/METADATA
pylint_single_element_destructuring-0.1.1.dist-info/RECORD
