Metadata-Version: 2.1
Name: pylint-single-element-destructuring
Version: 0.1.1
Summary: 
Author: d1618033
Requires-Python: >=3.6,<4.0
Classifier: Programming Language :: Python :: 3
Classifier: Programming Language :: Python :: 3.6
Classifier: Programming Language :: Python :: 3.7
Classifier: Programming Language :: Python :: 3.8
Requires-Dist: astroid (>=2.3.3,<3.0.0)
Requires-Dist: pylint (>=2.4.4,<3.0.0)
